CHANGES.rst
LICENSE
MANIFEST.in
README.rst
setup.py
mirte.egg-info/PKG-INFO
mirte.egg-info/SOURCES.txt
mirte.egg-info/dependency_links.txt
mirte.egg-info/entry_points.txt
mirte.egg-info/not-zip-safe
mirte.egg-info/requires.txt
mirte.egg-info/top_level.txt
src/__init__.py
src/core.py
src/main.py
src/mirteFile.py
src/threadPool.py