Metadata-Version: 1.0
Name: mirte
Version: 0.1.8
Summary: Runtime module framework
Home-page: http://github.com/bwesterb/mirte/
Author: Bas Westerbaan
Author-email: bas@westerbaan.name
License: UNKNOWN
Platform: UNKNOWN
